[
  {
    "week": "第1周（1-7天）",
    "goal": "搭建世界观的“可复用底盘”而不是只做零碎实验。",
    "metrics": [
      "推进 3 次以上“问题→检验→修订”学习循环，且每次都有结论。",
      "补一页 7 天世界观日志（至少 5 条高价值记录）。",
      "把“学习投入 / 输出 / 复盘”用一页卡片写出来。"
    ],
    "risks": [
      "只关注工具名和速度，忽略学习目标。",
      "重复做任务但没有留下验证证据。",
      "把 AI 输出当事实，不做复核。"
    ],
    "action": "写一篇 500 字世界观实践周报，附 1 条证据链。"
  },
  {
    "week": "第2周（8-14天）",
    "goal": "把一次性体验升级为稳定的“流程习惯”。",
    "metrics": [
      "固定 2 个高频任务，并为其形成标准输入模板。",
      "每个模板至少跑通 2 次，平均耗时下降 20% 以上。",
      "每次输出都补完整 3 元素复盘：来源、反例、下次改法。"
    ],
    "risks": [
      "重复新增工具导致流程分心。",
      "模板跑不通却仍强行继续。",
      "没有把失误写进下一版改进。"
    ],
    "action": "把一个模板沉淀为“可复用的 SOP”并公开给自己回看。"
  },
  {
    "week": "第3周（15-21天）",
    "goal": "引入“结果质量”与“合规边界”评估。",
    "metrics": [
      "至少做 1 次国内外模型对比，输出优缺点与适配点。",
      "每项作品明确 2 个验收标准和 1 个红线条款。",
      "建立风险登记表并每天下午补 1 条更新。"
    ],
    "risks": [
      "只比速度，不比准确性与可复核性。",
      "忽略隐私、版权、来源可追踪性。",
      "把高风险问题外包给模型。"
    ],
    "action": "做 1 个“模型/场景对照”实验，并给出决策建议。"
  },
  {
    "week": "第4周（22-30天）",
    "goal": "输出可以展示和复用的能力资产。",
    "metrics": [
      "产出 1 个可复用作品（视频/课程摘要/脚本/小工具）。",
      "提交 1 次公开复盘：1 条批评 + 1 次修订。",
      "将 30 天数据转成可持续执行的下一月动作清单。"
    ],
    "risks": [
      "沉迷“完美作品”导致长期拖延。",
      "只做一次性成果，不可复制。",
      "没有把风险和改进项闭环。"
    ],
    "action": "把这4周成果做成可复制模板页，明后月直接沿用。"
  }
]
